resource_monitor_scanner/gui.py
resource_monitor_scanner/main.py
resource_monitor_scanner-0.1.0.dist-info/LICENSE
resource_monitor_scanner-0.1.0.dist-info/METADATA
resource_monitor_scanner-0.1.0.dist-info/WHEEL
resource_monitor_scanner-0.1.0.dist-info/RECORD
