Metadata-Version: 2.1
Name: resource-monitor-scanner
Version: 0.1.0
Summary: 
License: MIT
Author: JavierOramas
Author-email: javiale2000@gmail.com
Requires-Python: >=3.10,<3.12
Classifier: License :: OSI Approved :: MIT License
Classifier: Programming Language :: Python :: 3
Classifier: Programming Language :: Python :: 3.10
Classifier: Programming Language :: Python :: 3.11
Requires-Dist: matplotlib (>=3.7.2,<4.0.0)
Requires-Dist: pandas (>=1.5.3,<2.0.0)
Requires-Dist: psutil (>=5.9.4,<6.0.0)
Requires-Dist: py3nvml (>=0.2.7,<0.3.0)
Requires-Dist: seaborn (>=0.12,<0.13)
Requires-Dist: streamlit (>=1.24.0,<2.0.0)
